linaix/__init__.py
linaix/linaix.py
linaix/providers.py
linaix-0.1.4.dist-info/licenses/license
linaix-0.1.4.dist-info/METADATA
linaix-0.1.4.dist-info/WHEEL
linaix-0.1.4.dist-info/entry_points.txt
linaix-0.1.4.dist-info/top_level.txt
linaix-0.1.4.dist-info/RECORD
