Metadata-Version: 2.4
Name: linaix
Version: 0.1.4
Summary: Cross-platform command generator from natural language (Linux/macOS/Windows)
Home-page: https://github.com/AdirAli/linaix
Author: Adir Ali Yerima
Maintainer: Adir Ali Yerima
License: MIT
Project-URL: Homepage, https://github.com/AdirAli/linaix
Project-URL: Repository, https://github.com/AdirAli/linaix
Project-URL: Documentation, https://github.com/AdirAli/linaix#readme
Project-URL: Bug Tracker, https://github.com/AdirAli/linaix/issues
Keywords: terminal,linux,nlp,cli
Classifier: Development Status :: 3 - Alpha
Classifier: Intended Audience :: Developers
Classifier: License :: OSI Approved :: MIT License
Classifier: Operating System :: OS Independent
Classifier: Programming Language :: Python :: 3
Classifier: Programming Language :: Python :: 3.7
Classifier: Programming Language :: Python :: 3.8
Classifier: Programming Language :: Python :: 3.9
Classifier: Programming Language :: Python :: 3.10
Classifier: Programming Language :: Python :: 3.11
Requires-Python: >=3.7
License-File: license
Requires-Dist: google-genai>=1.0.0
Requires-Dist: openai>=1.0.0
Provides-Extra: dev
Requires-Dist: pytest>=6.0; extra == "dev"
Requires-Dist: pytest-cov>=2.0; extra == "dev"
Requires-Dist: black>=21.0; extra == "dev"
Requires-Dist: flake8>=3.8; extra == "dev"
Requires-Dist: mypy>=0.800; extra == "dev"
Dynamic: home-page
Dynamic: license-file
Dynamic: requires-python
